ezwmails/__init__.py
ezwmails/funciones.py
ezwmails-1.0.1.dist-info/METADATA
ezwmails-1.0.1.dist-info/WHEEL
ezwmails-1.0.1.dist-info/top_level.txt
ezwmails-1.0.1.dist-info/RECORD
