Metadata-Version: 2.4
Name: ezwmails
Version: 1.0.1
Summary: Ready to go implementation for sending emails with python, a simple wrapper for stmp
Home-page: https://github.com/alan1x/ezwmails.git
Author: alan1x
Dynamic: author
Dynamic: description
Dynamic: description-content-type
Dynamic: home-page
Dynamic: summary
